hooktheory_mcp/__init__.py
hooktheory_mcp-0.2.3.dist-info/WHEEL
hooktheory_mcp-0.2.3.dist-info/entry_points.txt
hooktheory_mcp-0.2.3.dist-info/METADATA
hooktheory_mcp-0.2.3.dist-info/RECORD
