Metadata-Version: 2.3
Name: hooktheory-mcp
Version: 0.2.3
Summary: Model Context Protocol server for Hooktheory API integration - enables agents to query chord progressions and music theory data
Keywords: mcp,model-context-protocol,hooktheory,music,chords,ai
Author: Gabriel Guerin
Author-email: Gabriel Guerin <gabriel.guerin.a@gmail.com>
License: MIT
Classifier: Development Status :: 4 - Beta
Classifier: Intended Audience :: Developers
Classifier: Topic :: Software Development :: Libraries :: Python Modules
Classifier: Topic :: Multimedia :: Sound/Audio :: Analysis
Classifier: License :: OSI Approved :: MIT License
Classifier: Programming Language :: Python :: 3
Classifier: Programming Language :: Python :: 3.11
Classifier: Programming Language :: Python :: 3.12
Requires-Dist: mcp>=1.23.3
Requires-Dist: httpx>=0.28.0
Requires-Dist: pydantic>=2.0.0
Requires-Python: >=3.11
Project-URL: Documentation, https://github.com/gabguerin/hooktheory-mcp#readme
Project-URL: Homepage, https://github.com/gabguerin/hooktheory-mcp
Project-URL: Issues, https://github.com/gabguerin/hooktheory-mcp/issues
Project-URL: Repository, https://github.com/gabguerin/hooktheory-mcp
